README.txt
SqliteKVStore.py
URLShortener.py
purls.py
setup.py
purls.egg-info/PKG-INFO
purls.egg-info/SOURCES.txt
purls.egg-info/dependency_links.txt
purls.egg-info/requires.txt
purls.egg-info/top_level.txt