Metadata-Version: 1.0
Name: purls
Version: 0.0.2
Summary: Personal URL shortener for personal domains.
Home-page: https://github.com/hq6/purls
Author: Henry Qin
Author-email: root@hq6.me
License: MIT
Platform: Any Platform supporting ANSI escape codes
